{
    "week_number": 68,
    "timestamp": "2026-03-12T14:45:47.464464",
    "companies": {
        "TitanForge Defense": {
            "market_cap": 1.0023685501844473,
            "sector": 310,
            "country": "Lexion"
        },
        "Cerebra AI Systems": {
            "market_cap": 1.0005161761072128,
            "sector": 420,
            "country": "Lexion"
        },
        "Aether Aerospace": {
            "market_cap": 1.0125975193641235,
            "sector": 260,
            "country": "Lexion"
        },
        "IronCore Mining": {
            "market_cap": 1.0022169586509668,
            "sector": 190,
            "country": "Lexion"
        },
        "NexaDrive Motors": {
            "market_cap": 1.0161294172552595,
            "sector": 145,
            "country": "Lexion"
        },
        "Voltrix Nuclear": {
            "market_cap": 1.0103219033347481,
            "sector": 175,
            "country": "Lexion"
        },
        "OmniSteel Heavy Industries": {
            "market_cap": 1.004187754441515,
            "sector": 150,
            "country": "Lexion"
        },
        "LexAgri Systems": {
            "market_cap": 1.0060741044514276,
            "sector": 70,
            "country": "Lexion"
        },
        "IonGrid Storage": {
            "market_cap": 1.0038822953105824,
            "sector": 350,
            "country": "Solmere Collective"
        },
        "HelioDyne Renewables": {
            "market_cap": 1.0030458313008863,
            "sector": 240,
            "country": "Solmere Collective"
        },
        "Verdant BioLabs": {
            "market_cap": 1.011690845712659,
            "sector": 180,
            "country": "Solmere Collective"
        },
        "EcoTransit Systems": {
            "market_cap": 1.0026318141958193,
            "sector": 120,
            "country": "Solmere Collective"
        },
        "GreenCore Materials": {
            "market_cap": 1.0046161032468928,
            "sector": 95,
            "country": "Solmere Collective"
        },
        "Helios Robotics": {
            "market_cap": 1.014766501678778,
            "sector": 310,
            "country": "Helios Pact"
        },
        "Synapse Automation": {
            "market_cap": 1.0101213273970013,
            "sector": 220,
            "country": "Helios Pact"
        },
        "QuantumWorks Labs": {
            "market_cap": 1.0105899629414996,
            "sector": 400,
            "country": "Helios Pact"
        },
        "PetroDrav Energy": {
            "market_cap": 1.0000638878379324,
            "sector": 220,
            "country": "Dravosk Union"
        },
        "Granite Crown Mining": {
            "market_cap": 1.0036344316696912,
            "sector": 95,
            "country": "Dravosk Union"
        },
        "DravRail Logistics": {
            "market_cap": 1.0006522234835982,
            "sector": 60,
            "country": "Dravosk Union"
        },
        "Borealis Drilling": {
            "market_cap": 1.002144912784623,
            "sector": 130,
            "country": "Dravosk Union"
        },
        "Union Gas Export": {
            "market_cap": 1.0017504422032506,
            "sector": 115,
            "country": "Dravosk Union"
        },
        "Velkar Energy Holdings": {
            "market_cap": 1.0001685829443707,
            "sector": 12,
            "country": "Velkar Basin"
        },
        "Cobalt Frontier Ltd": {
            "market_cap": 1.001547311111009,
            "sector": 18,
            "country": "Velkar Basin"
        },
        "Basin Transport Group": {
            "market_cap": 1.001001515228759,
            "sector": 9,
            "country": "Velkar Basin"
        },
        "Arkenfall Copper": {
            "market_cap": 1.001811915469688,
            "sector": 70,
            "country": "Arkenfall"
        },
        "HighPeak Steel": {
            "market_cap": 1.00355317878058,
            "sector": 95,
            "country": "Arkenfall"
        },
        "Alpine Transit Co": {
            "market_cap": 1.0051291373929496,
            "sector": 55,
            "country": "Arkenfall"
        },
        "SkyBridge Financial": {
            "market_cap": 1.0023299327299804,
            "sector": 285,
            "country": "Varin Republic"
        },
        "BlueHarbor Shipping": {
            "market_cap": 1.0078835405902407,
            "sector": 140,
            "country": "Varin Republic"
        },
        "Mercury Exchange Group": {
            "market_cap": 1.0059246043320276,
            "sector": 125,
            "country": "Varin Republic"
        },
        "Virex Technologies": {
            "market_cap": 1.0,
            "sector": 210,
            "country": "Varin Republic"
        },
        "OceanGate Insurance": {
            "market_cap": 1.0007225228054337,
            "sector": 90,
            "country": "Varin Republic"
        },
        "Selvarin Global Bank": {
            "market_cap": 1.0013752271717522,
            "sector": 250,
            "country": "Selvarin"
        },
        "Haven Asset Management": {
            "market_cap": 1.0033236061702446,
            "sector": 175,
            "country": "Selvarin"
        },
        "SecureVault Holdings": {
            "market_cap": 1.001830680917221,
            "sector": 120,
            "country": "Selvarin"
        },
        "KarthWorks Manufacturing": {
            "market_cap": 1.0055474661248247,
            "sector": 110,
            "country": "Karth Dominion"
        },
        "NovaConstruct Infrastructure": {
            "market_cap": 1.0,
            "sector": 95,
            "country": "Karth Dominion"
        },
        "EastWeave Textiles": {
            "market_cap": 1.0003909424098267,
            "sector": 45,
            "country": "Karth Dominion"
        },
        "Dominion Plastics": {
            "market_cap": 1.0012520636311417,
            "sector": 60,
            "country": "Karth Dominion"
        },
        "UrbanRise Development": {
            "market_cap": 1.001782221931294,
            "sector": 70,
            "country": "Karth Dominion"
        },
        "PolyChem Tazbek": {
            "market_cap": 1.000861982334456,
            "sector": 65,
            "country": "Tazbek Industrial Zone"
        },
        "Threadline Textiles": {
            "market_cap": 1.0039454563786696,
            "sector": 38,
            "country": "Tazbek Industrial Zone"
        },
        "SunPort Assembly": {
            "market_cap": 1.0113613399729537,
            "sector": 72,
            "country": "Tazbek Industrial Zone"
        },
        "HarborLight Exports": {
            "market_cap": 1.0002489111781832,
            "sector": 50,
            "country": "Tazbek Industrial Zone"
        },
        "Baresh Textiles": {
            "market_cap": 1.0011852165881552,
            "sector": 25,
            "country": "Baresh Dominion"
        },
        "IronHands Tooling": {
            "market_cap": 1.0007303367766813,
            "sector": 40,
            "country": "Baresh Dominion"
        },
        "Port Baresh Logistics": {
            "market_cap": 1.0001297586498994,
            "sector": 30,
            "country": "Baresh Dominion"
        },
        "Orlith Canal Corporation": {
            "market_cap": 1.0148467893469926,
            "sector": 300,
            "country": "Orlith Strait Authority"
        },
        "StraitShield Maritime Security": {
            "market_cap": 1.0001173350376575,
            "sector": 110,
            "country": "Orlith Strait Authority"
        },
        "Orlith Port Holdings": {
            "market_cap": 1.000433243704353,
            "sector": 95,
            "country": "Orlith Strait Authority"
        },
        "GoldenFields Agro": {
            "market_cap": 1.0047470812634327,
            "sector": 28,
            "country": "Mavaria"
        },
        "MavaRail Freight": {
            "market_cap": 1.0,
            "sector": 15,
            "country": "Mavaria"
        },
        "AgriNova Fertilizers": {
            "market_cap": 1.0003770457018237,
            "sector": 40,
            "country": "Mavaria"
        },
        "HarvestBond Commodities": {
            "market_cap": 1.0015867140841286,
            "sector": 22,
            "country": "Mavaria"
        },
        "Zarethia Resorts": {
            "market_cap": 1.0050243899197682,
            "sector": 85,
            "country": "Zarethia"
        },
        "AzureAir Travel": {
            "market_cap": 1.000795392732722,
            "sector": 75,
            "country": "Zarethia"
        },
        "Sapphire Coast Holdings": {
            "market_cap": 1.0026940296400666,
            "sector": 60,
            "country": "Zarethia"
        },
        "Korynthia Cloud Systems": {
            "market_cap": 1.001487510273502,
            "sector": 280,
            "country": "Korynthia"
        },
        "NanoSpark Innovations": {
            "market_cap": 1.003268590883902,
            "sector": 210,
            "country": "Korynthia"
        },
        "CircuitWave Electronics": {
            "market_cap": 1.007961822854814,
            "sector": 150,
            "country": "Korynthia"
        },
        "Virelia Grain Co": {
            "market_cap": 1.0010367717880708,
            "sector": 75,
            "country": "Virelia"
        },
        "SunHarvest Oils": {
            "market_cap": 1.0043379921369722,
            "sector": 60,
            "country": "Virelia"
        },
        "GreenPasture Livestock": {
            "market_cap": 1.002692247099198,
            "sector": 50,
            "country": "Virelia"
        },
        "Draxmoor Arms": {
            "market_cap": 1.0,
            "sector": 190,
            "country": "Draxmoor"
        },
        "BlackForge Machinery": {
            "market_cap": 1.003601252165617,
            "sector": 130,
            "country": "Draxmoor"
        },
        "IronWall Logistics": {
            "market_cap": 1.0024458143204409,
            "sector": 85,
            "country": "Draxmoor"
        },
        "FrostCore Minerals": {
            "market_cap": 1.0041922894564284,
            "sector": 140,
            "country": "Norvane"
        },
        "PolarWind Energy": {
            "market_cap": 1.0059708715606583,
            "sector": 115,
            "country": "Norvane"
        },
        "Norvane Logistics": {
            "market_cap": 1.0040302711014868,
            "sector": 90,
            "country": "Norvane"
        },
        "Qandor National Oil": {
            "market_cap": 1.0114348752182571,
            "sector": 260,
            "country": "Qandor Emirate"
        },
        "DesertSky Airlines": {
            "market_cap": 1.0047963585980193,
            "sector": 95,
            "country": "Qandor Emirate"
        },
        "Sovereign Capital Holdings": {
            "market_cap": 1.000099847506992,
            "sector": 180,
            "country": "Qandor Emirate"
        }
    },
    "currencies": {
        "LX": 0.8977525335510614,
        "SLR": 1.0165179227236654,
        "HL": 1.0053108815715797,
        "DRV": 0.9345601149528417,
        "VLC": 0.9876529059328902,
        "ARK": 0.9345601149528417,
        "VRC": 0.9509970794877577,
        "SEL": 0.8837818869821106,
        "KTM": 1.064927351519142,
        "TZU": 1.0093576219704916,
        "BHP": 1.0637695697124847,
        "ORT": 0.9376737342698996,
        "MVA": 0.9659715546100189,
        "ZRD": 1.0170767660826978,
        "KYT": 1.047861795085632,
        "VFL": 0.9028703080653762,
        "DXM": 1.0205990906827784,
        "NRC": 0.9918645425064133,
        "QDR": 0.9345601149528417
    }
}